img_show/__init__.py
img_show/py.typed
img_show-0.2.0.dist-info/METADATA
img_show-0.2.0.dist-info/WHEEL
img_show-0.2.0.dist-info/licenses/LICENSE
img_show-0.2.0.dist-info/RECORD
