Metadata-Version: 2.4
Name: img-show
Version: 0.2.0
Summary: A opinionated tool for coercing data into something displayable
Project-URL: Homepage, https://github.com/belfner/img-show
Project-URL: Repository, https://github.com/belfner/img-show
Author-email: Ben Elfner <belfner@belfner.com>
License: MIT
License-File: LICENSE
Classifier: License :: OSI Approved :: MIT License
Classifier: Operating System :: Microsoft :: Windows
Classifier: Operating System :: Unix
Classifier: Programming Language :: Python :: 3
Classifier: Programming Language :: Python :: 3 :: Only
Classifier: Programming Language :: Python :: 3.8
Classifier: Programming Language :: Python :: 3.9
Classifier: Programming Language :: Python :: 3.10
Classifier: Programming Language :: Python :: 3.11
Classifier: Programming Language :: Python :: 3.12
Classifier: Programming Language :: Python :: Implementation :: CPython
Classifier: Topic :: Utilities
Requires-Python: >=3.8
Requires-Dist: numpy>=1.24.4
Requires-Dist: opencv-python>=4.11.0.86
